onvif_gui/__init__.py
onvif_gui/enums.py
onvif_gui/glwidget.py
onvif_gui/main.py
onvif_gui/manager.py
onvif_gui/player.py
onvif_gui/server.py
onvif_gui/components/__init__.py
onvif_gui/components/comboselector.py
onvif_gui/components/directoryselector.py
onvif_gui/components/diskmanager.py
onvif_gui/components/fileselector.py
onvif_gui/components/infodialog.py
onvif_gui/components/progress.py
onvif_gui/components/target.py
onvif_gui/components/thresholdslider.py
onvif_gui/components/warningbar.py
onvif_gui/panels/__init__.py
onvif_gui/panels/audio/__init__.py
onvif_gui/panels/audio/audiopanel.py
onvif_gui/panels/audio/modules/__init__.py
onvif_gui/panels/audio/modules/sample.py
onvif_gui/panels/camera/__init__.py
onvif_gui/panels/camera/cameralist.py
onvif_gui/panels/camera/camerapanel.py
onvif_gui/panels/camera/datastructures.py
onvif_gui/panels/camera/imagetab.py
onvif_gui/panels/camera/logindialog.py
onvif_gui/panels/camera/networktab.py
onvif_gui/panels/camera/ptztab.py
onvif_gui/panels/camera/snapshot.py
onvif_gui/panels/camera/systemtab.py
onvif_gui/panels/camera/videotab.py
onvif_gui/panels/file/__init__.py
onvif_gui/panels/file/controlpanel.py
onvif_gui/panels/file/filepanel.py
onvif_gui/panels/file/searchdialog.py
onvif_gui/panels/file/treeview.py
onvif_gui/panels/picture/__init__.py
onvif_gui/panels/picture/picturepanel.py
onvif_gui/panels/settings/__init__.py
onvif_gui/panels/settings/alarm.py
onvif_gui/panels/settings/discover.py
onvif_gui/panels/settings/general.py
onvif_gui/panels/settings/proxy.py
onvif_gui/panels/settings/settingspanel.py
onvif_gui/panels/settings/storage.py
onvif_gui/panels/video/__init__.py
onvif_gui/panels/video/videopanel.py
onvif_gui/panels/video/modules/__init__.py
onvif_gui/panels/video/modules/motion.py
onvif_gui/panels/video/modules/settings.py
onvif_gui/panels/video/modules/yolox.py
onvif_gui/panels/video/modules/common/__init__.py
onvif_gui/panels/video/modules/yolox/__init__.py
onvif_gui-3.3.4.dist-info/licenses/LICENSE
onvif_gui-3.3.4.dist-info/METADATA
onvif_gui-3.3.4.dist-info/WHEEL
onvif_gui-3.3.4.dist-info/entry_points.txt
onvif_gui-3.3.4.dist-info/top_level.txt
onvif_gui-3.3.4.dist-info/RECORD
