Metadata-Version: 2.4
Name: onvif-gui
Version: 3.3.4
Summary: A client gui for Onvif
Author: Stephen Rhodes
Author-email: Stephen Rhodes <sr99622@gmail.com>
License-Expression: Apache-2.0
Project-URL: Homepage, https://github.com/sr99622/libonvif
Project-URL: Bug Reports, https://github.com/sr99622/libonvif/issues
Keywords: sample,setuptools,development
Classifier: Development Status :: 5 - Production/Stable
Classifier: Intended Audience :: Developers
Classifier: Topic :: Software Development :: Build Tools
Classifier: Programming Language :: Python :: 3
Requires-Python: >=3.10
License-File: LICENSE
Requires-Dist: libonvif==3.2.8
Requires-Dist: avio==3.2.7
Requires-Dist: kankakee==1.0.4
Requires-Dist: numpy
Requires-Dist: loguru
Requires-Dist: opencv-python-headless
Requires-Dist: PyQt6-Qt6
Requires-Dist: pyqt6
Requires-Dist: requests
Dynamic: author
Dynamic: license-file
Dynamic: requires-python
